mkdocs_atom_plugin/__about__.py
mkdocs_atom_plugin/__init__.py
mkdocs_atom_plugin/feed.py
mkdocs_atom_plugin/plugin.py
mkdocs_atom_plugin/util.py
mkdocs_atom_plugin/templates/atom.xml.jinja2
mkdocs_atom_plugin-0.0.5.dist-info/METADATA
mkdocs_atom_plugin-0.0.5.dist-info/WHEEL
mkdocs_atom_plugin-0.0.5.dist-info/entry_points.txt
mkdocs_atom_plugin-0.0.5.dist-info/top_level.txt
mkdocs_atom_plugin-0.0.5.dist-info/RECORD
