Metadata-Version: 2.1
Name: mkdocs-atom-plugin
Version: 0.0.5
Summary: atom feeed generator for MkDocs
Home-page: https://github.com/maedadev/mkdocs-atom-plugin
License: UNKNOWN
Platform: UNKNOWN
Classifier: Programming Language :: Python :: 3
Classifier: License :: OSI Approved :: MIT License
Classifier: Operating System :: OS Independent
Requires-Python: <4,>=3.6
